NaijaBet_Api/__init__.py
NaijaBet_Api/__main__.py
NaijaBet_Api/id.py
NaijaBet_Api/bookmakers/BaseClass.py
NaijaBet_Api/bookmakers/__init__.py
NaijaBet_Api/bookmakers/bet9ja.py
NaijaBet_Api/bookmakers/betking.py
NaijaBet_Api/bookmakers/nairabet.py
NaijaBet_Api/utils/__init__.py
NaijaBet_Api/utils/bet9ja_normalizer.json
NaijaBet_Api/utils/betking_normalizer.json
NaijaBet_Api/utils/jsonpaths.py
NaijaBet_Api/utils/logger.py
NaijaBet_Api/utils/nairabet_normalizer.json
NaijaBet_Api/utils/normalizer.py
NaijaBet_Api-0.2.17.dist-info/LICENSE
NaijaBet_Api-0.2.17.dist-info/METADATA
NaijaBet_Api-0.2.17.dist-info/WHEEL
NaijaBet_Api-0.2.17.dist-info/top_level.txt
NaijaBet_Api-0.2.17.dist-info/RECORD
