Metadata-Version: 2.1
Name: NaijaBet-Api
Version: 0.2.17
Summary: A wrapper around the API of Nigerias major betting sites
Home-page: https://github.com/jayteealao/Naijabet_Api
Author: graphitenerd
Author-email: jayteealao@gmail.com
Project-URL: Bug Tracker, https://github.com/jayteealao/Naijabet_Api/issues
Classifier: Programming Language :: Python :: 3
Classifier: License :: OSI Approved :: MIT License
Classifier: Operating System :: OS Independent
License-File: LICENSE
